README.md
setup.cfg
setup.py
distributions_2f46a24e/Binomialdistribution.py
distributions_2f46a24e/Gaussiandistribution.py
distributions_2f46a24e/Generaldistribution.py
distributions_2f46a24e/__init__.py
distributions_2f46a24e.egg-info/PKG-INFO
distributions_2f46a24e.egg-info/SOURCES.txt
distributions_2f46a24e.egg-info/dependency_links.txt
distributions_2f46a24e.egg-info/not-zip-safe
distributions_2f46a24e.egg-info/top_level.txt